natn/__about__.py
natn/__init__.py
natn/config.py
natn/clipboard/__init__.py
natn/core/__init__.py
natn/network/__init__.py
natn/package_manager/__init__.py
natn-0.0.10.dist-info/METADATA
natn-0.0.10.dist-info/WHEEL
natn-0.0.10.dist-info/licenses/LICENSE.txt
natn-0.0.10.dist-info/RECORD
